xiaoming_weather
