Metadata-Version: 2.1
Name: xiaoming-weather
Version: 1.0.2
Summary: Xiaoming weather provides personalized weather data strings for chinese user.
Home-page: https://github.com/dangoms/xiaoming-weather
Author: zhangyadong
Author-email: zhangyd@live.com
License: MIT
Platform: UNKNOWN
Classifier: License :: OSI Approved :: MIT License
Classifier: Programming Language :: Python :: 3
Classifier: Programming Language :: Python :: 3.7
